{
  "slug": "eye-i-aye-yuh",
  "title": "eye i aye yuh",
  "type": "lyrics",
  "artist": "akabilly",
  "year": "unknown",
  "date": null,
  "description": "Lyrics from eye i aye yuh",
  "access": {
    "original": "author-locked",
    "permitted": [
      "fork",
      "remix",
      "annotate",
      "critique",
      "quote",
      "share"
    ]
  },
  "audioSrc": null,
  "externalLinks": [],
  "body": "created on may 18, 2018\n\n#releases\n\nhttps://open.spotify.com/album/52na8ipcvvlwlmgh1vyqtk?si=c1sypfcatv-fa0vbjstnia&dl_branch=1\n\n#soundcloud https://soundcloud.com/billy-moreno/1-ayayayah\n\nv2\n\nm4a:\n\nsoundcloud mastered with aurora at 82pct\n\n resolve: this file is empty after uploading\n\n\n\n\n\nthe mouth the mind the hand the heart\nthis is how i find my art\nthe aye the eye the i the ah\nthe words i use to wonder why\ni can't see beyond the pines\ni ain't signin dotted lines\nif you trust me this is why\ncuz you watch me learn to fly\nand i can bend and i can break\ncareful bout the road i take\nknow i mean the things i say\ncuz i'm tryin to find a way\nwhen i find it can't be stopped\ntil i reach the very top\nof the mountain but who's countin\nwe all climbin different ones\nup the mountain down the mountain\nfrom the valleys to the sum\nit's struggle, it's a grind\nbangin with the rocks i mined\nthe feet the fang the fingertip\nthis is how i keep my grip\nit's struggle, it's a grind\nbangin with the rocks i mined\nthe feet the fang the fingertip\nthis is how i keep my grip\nthe aye the eye the i the ah\nwindows through which i watch the sky\nyada yada yada ya\nit goes in here and out this side\nthe mouth the mind the hand the heart\nthis is how i built my ark\nthe aye the eye the i the ah\nthe would i use to keep me try\nduck duck goose goose\nthe words the birds that i let loose\ni can count twos\nif you can't come then what's the use\nthe u, the you, the ewe, the yew\ncuz you're the root i come back to\nthe mouth the mind the hand the heart\nthis is how i do my part",
  "remixes": [],
  "remixConfig": {
    "allowPublicSubmission": false,
    "featured": null,
    "abTest": null
  },
  "tags": [
    "lyrics"
  ]
}