{
  "slug": "fault-lines",
  "title": "fault lines",
  "type": "lyrics",
  "artist": "akabilly",
  "year": "unknown",
  "date": null,
  "description": "Lyrics from fault lines",
  "access": {
    "original": "author-locked",
    "permitted": [
      "fork",
      "remix",
      "annotate",
      "critique",
      "quote",
      "share"
    ]
  },
  "audioSrc": null,
  "externalLinks": [],
  "body": "fault line lyrics\n\nlisten\ni'm out here spittin cuz i'm gettin in touch with people\nthat's my mission\ndo you\nit's cool\nbut please excuse these bricks\ni'm building a cathedral with acoustics louder than boomsticks\nout in the boondocks cuz that's how my mind rocks\nwhen i'm on the time clock try not to grind rocks\nclimb until i top\ndive until i stop\nmove until i drop\nthe truth is a liar\nthe roof is on fire\nbut we don't need water\nit's a funeral pyre for a feudal empire\nand i'm proud of the future\ni can see that it's brighter\ni see with my eyes closed, i know i'm a writer\nthe trush about my flow, i know i'm a liar\nbut wherever i go the water gets higher\nthat's how i know i'm alright\ni know i'm not right but i know i'm alright\nthat's where i go when i write\nthat's where i go when i'm wrong\ni'm not just going along not knowing the song\ni need to sing to survive the salt mine\nhow the fuck else we gonna find the fault line\nclimb to the surface\nsee if it's worth it\nto walk on our own two\nwith personal purpose\n\nlinks\n\nsoundcloud: https://soundcloud.com/billy-moreno/fault-lines\n\n lyrics\n\n credits\n\nbjorn vader - \"certain magic\"\n\n metadata\n\n permissions\n\ntwitter:\n\ninstagram:\n\ntiktok:\n\nyoutube:\n\nart\n\n\n\nhashtags\n\nloose hop, slip hop",
  "remixes": [],
  "remixConfig": {
    "allowPublicSubmission": false,
    "featured": null,
    "abTest": null
  },
  "tags": [
    "lyrics"
  ]
}