{
  "slug": "high-road",
  "title": "high road",
  "type": "lyrics",
  "artist": "akabilly",
  "year": "unknown",
  "date": null,
  "description": "Lyrics from high road",
  "access": {
    "original": "author-locked",
    "permitted": [
      "fork",
      "remix",
      "annotate",
      "critique",
      "quote",
      "share"
    ]
  },
  "audioSrc": null,
  "externalLinks": [],
  "body": "i get high as i can get and yet\ni always find there's another step to take before i can see it all\nstill y'all all already look so small\nnever see your faces except in pictures\nsame with god's except it's scriptures\nplay the odds cuz that's all they give\ndeal with the pain that the draw deliver\nread the cards like my women taught\nmap the lines from the ways they brought me\nup to the moment that i found my footing\nnow i give back with the work i put in\nget down to business, gotta earn a living\nlive down what it is, you can turn a prophet\nall you gotta do is learn to give in\nthe wheel will turn, it ain't your turn to stop it\n\nwav:",
  "remixes": [],
  "remixConfig": {
    "allowPublicSubmission": false,
    "featured": null,
    "abTest": null
  },
  "tags": [
    "lyrics"
  ]
}